termsnake/snake.py
termsnake-0.0.1.dist-info/LICENSE
termsnake-0.0.1.dist-info/METADATA
termsnake-0.0.1.dist-info/WHEEL
termsnake-0.0.1.dist-info/entry_points.txt
termsnake-0.0.1.dist-info/top_level.txt
termsnake-0.0.1.dist-info/RECORD
