Metadata-Version: 2.1
Name: termsnake
Version: 0.0.1
Summary: A Python package that creates a nice snake game for your terminal.
Home-page: https://github.com/Python3-8/termsnake
Author: Pranav Balaji Pooruli
Author-email: pranav.pooruli@gmail.com
License: MIT
Platform: UNKNOWN
Classifier: License :: OSI Approved :: MIT License
Classifier: Programming Language :: Python :: 3
Classifier: Programming Language :: Python :: 3.8
